thegraph_handlers/__init__.py
thegraph_handlers/__version__.py
thegraph_handlers/_exceptions.py
thegraph_handlers/_protocols.py
thegraph_handlers/_subgraph_client.py
thegraph_handlers/_utils.py
thegraph_handlers/abstract_handler.py
thegraph_handlers/models.py
thegraph_handlers/dodoex_v2/__init__.py
thegraph_handlers/dodoex_v2/_types.py
thegraph_handlers/dodoex_v2/base_swap.py
thegraph_handlers/dodoex_v2/dodoex_v2.py
thegraph_handlers/dodoex_v2/parsers.py
thegraph_handlers/dodoex_v2/queries.py
thegraph_handlers/mirror/__init__.py
thegraph_handlers/mirror/_types.py
thegraph_handlers/mirror/data.py
thegraph_handlers/mirror/mirror.py
thegraph_handlers/mirror/mirror_helper.py
thegraph_handlers/mirror/model.py
thegraph_handlers/mirror/parsers.py
thegraph_handlers/mirror/queries.py
thegraph_handlers/shared/__init__.py
thegraph_handlers/shared/_types.py
thegraph_handlers/shared/base_swap.py
thegraph_handlers/shared/dispatch.py
thegraph_handlers/shared/queries.py
thegraph_handlers/sushiswap/__init__.py
thegraph_handlers/sushiswap/parsers.py
thegraph_handlers/sushiswap/sushiswap.py
thegraph_handlers/uniswap_v2/__init__.py
thegraph_handlers/uniswap_v2/parsers.py
thegraph_handlers/uniswap_v2/uniswap_v2.py
thegraph_handlers/uniswap_v3/UNI_v3_funcs.py
thegraph_handlers/uniswap_v3/__init__.py
thegraph_handlers/uniswap_v3/_types.py
thegraph_handlers/uniswap_v3/parsers.py
thegraph_handlers/uniswap_v3/queries.py
thegraph_handlers/uniswap_v3/uniswap_v3.py
thegraph_handlers/uniswap_v3/univ3_funcs.py
ck_thegraph_handlers-0.0.15.dist-info/METADATA
ck_thegraph_handlers-0.0.15.dist-info/WHEEL
ck_thegraph_handlers-0.0.15.dist-info/top_level.txt
ck_thegraph_handlers-0.0.15.dist-info/RECORD
