Metadata-Version: 2.1
Name: ck-thegraph-handlers
Version: 0.0.15
Summary: Integrations of Ethereum services through https://thegraph.com
Home-page: UNKNOWN
Author: crypkit
Author-email: info@crypkit.com
License: UNKNOWN
Platform: UNKNOWN
Requires-Dist: anyio
Requires-Dist: attrs
Requires-Dist: httpx
Requires-Dist: web3
Requires-Dist: typing-extensions
Provides-Extra: all
Requires-Dist: tox ; extra == 'all'
Requires-Dist: pytest ; extra == 'all'
Requires-Dist: pytest-asyncio ; extra == 'all'
Requires-Dist: pytest-vcr ; extra == 'all'
Provides-Extra: dev
Requires-Dist: tox ; extra == 'dev'
Provides-Extra: test
Requires-Dist: pytest ; extra == 'test'
Requires-Dist: pytest-asyncio ; extra == 'test'
Requires-Dist: pytest-vcr ; extra == 'test'
